bitcoincash/__init__.py
bitcoincash/base58.py
bitcoincash/bloom.py
bitcoincash/cashaddr.py
bitcoincash/messages.py
bitcoincash/net.py
bitcoincash/rpc.py
bitcoincash/signature.py
bitcoincash/signmessage.py
bitcoincash/wallet.py
bitcoincash/core/__init__.py
bitcoincash/core/_bignum.py
bitcoincash/core/key.py
bitcoincash/core/schnorr.py
bitcoincash/core/script.py
bitcoincash/core/scripteval.py
bitcoincash/core/serialize.py
bitcoincash/electrum/__init__.py
bitcoincash/electrum/client.py
bitcoincash/electrum/constants.py
bitcoincash/electrum/exc.py
bitcoincash/electrum/protocol.py
bitcoincash/electrum/svr_info.py
bitcoincash/tests/__init__.py
bitcoincash/tests/fakebitcoinproxy.py
bitcoincash/tests/test_base58.py
bitcoincash/tests/test_bloom.py
bitcoincash/tests/test_cashaddrenc.py
bitcoincash/tests/test_checkblock.py
bitcoincash/tests/test_core.py
bitcoincash/tests/test_electrum.py
bitcoincash/tests/test_fakebitcoinproxy.py
bitcoincash/tests/test_key.py
bitcoincash/tests/test_messages.py
bitcoincash/tests/test_net.py
bitcoincash/tests/test_rpc.py
bitcoincash/tests/test_schnorr.py
bitcoincash/tests/test_script.py
bitcoincash/tests/test_scripteval.py
bitcoincash/tests/test_serialize.py
bitcoincash/tests/test_sighash.py
bitcoincash/tests/test_signmessage.py
bitcoincash/tests/test_transactions.py
bitcoincash/tests/test_wallet.py
bitcoincash-0.1.5.dist-info/LICENSE
bitcoincash-0.1.5.dist-info/METADATA
bitcoincash-0.1.5.dist-info/WHEEL
bitcoincash-0.1.5.dist-info/top_level.txt
bitcoincash-0.1.5.dist-info/RECORD
