Metadata-Version: 2.1
Name: bitcoincash
Version: 0.1.5
Summary: The Swiss Army Knife of the Bitcoin Cash protocol.
Home-page: https://bitcoincash.network/python/
License: UNKNOWN
Keywords: bitcoin cash bch bitcoincash
Platform: UNKNOWN
Classifier: Programming Language :: Python :: 3
Classifier: License :: OSI Approved :: GNU Lesser General Public License v3 or later (LGPLv3+)
Requires-Python: >3.6.7
